meteo_si/__init__.py
meteo_si/constants.py
meteo_si/density.py
meteo_si/due.py
meteo_si/humidity.py
meteo_si/meteo_si.py
meteo_si/temperature.py
meteo_si/version.py
meteo_si/wind.py
meteo_si/tests/__init__.py
meteo_si/tests/test_meteo_si.py
meteo_si-0.1.1.dev0.dist-info/METADATA
meteo_si-0.1.1.dev0.dist-info/RECORD
meteo_si-0.1.1.dev0.dist-info/WHEEL
meteo_si-0.1.1.dev0.dist-info/top_level.txt
