Metadata-Version: 2.1
Name: meteo-si
Version: 0.1.1.dev0
Summary: meteo_si: Meteo SI is a collection of meteorological formulas
Home-page: http://github.com/maahn/meteo_si
Author: Maximilian Maahn
Author-email: maximilian.maahn@colorado.edu
Maintainer: Maximilian Maahn
Maintainer-email: maximilian.maahn@colorado.edu
License: MIT
Platform: OS Independent
Classifier: Development Status :: 3 - Alpha
Classifier: Environment :: Console
Classifier: Intended Audience :: Science/Research
Classifier: License :: OSI Approved :: MIT License
Classifier: Operating System :: OS Independent
Classifier: Programming Language :: Python
Classifier: Topic :: Scientific/Engineering
Requires: numpy
Requires-Dist: numpy
